pitchmeld/__init__.py
pitchmeld/sdk_python3_module.cpython-311-darwin.so
pitchmeld/tests/license_test.py
pitchmeld/tests/__init__.py
pitchmeld/tests/nolicense_test.py
pitchmeld/tests/utils.py
pitchmeld/tests/test_data/wav/arctic_b0518.wav
pitchmeld/doc/LICENSE.md
pitchmeld/doc/transformation.html
pitchmeld/doc/index.html
pitchmeld/doc/license.html
pitchmeld/doc/support.html
pitchmeld/doc/searchindex.js
pitchmeld/doc/genindex.html
pitchmeld/doc/attributions.html
pitchmeld/doc/misc.html
pitchmeld/doc/search.html
pitchmeld/doc/installation.html
pitchmeld/doc/objects.inv
pitchmeld/doc/_sources/support.rst.txt
pitchmeld/doc/_sources/attributions.rst.txt
pitchmeld/doc/_sources/installation.rst.txt
pitchmeld/doc/_sources/transformation.rst.txt
pitchmeld/doc/_sources/misc.rst.txt
pitchmeld/doc/_sources/index.rst.txt
pitchmeld/doc/_sources/license.rst.txt
pitchmeld/doc/_static/plus.png
pitchmeld/doc/_static/sphinx_highlight.js
pitchmeld/doc/_static/icon.png
pitchmeld/doc/_static/favicon.ico
pitchmeld/doc/_static/documentation_options.js
pitchmeld/doc/_static/searchtools.js
pitchmeld/doc/_static/debug.css
pitchmeld/doc/_static/check-solid.svg
pitchmeld/doc/_static/clipboard.min.js
pitchmeld/doc/_static/file.png
pitchmeld/doc/_static/english-stemmer.js
pitchmeld/doc/_static/copybutton.js
pitchmeld/doc/_static/base-stemmer.js
pitchmeld/doc/_static/icon64.png
pitchmeld/doc/_static/language_data.js
pitchmeld/doc/_static/copy-button.svg
pitchmeld/doc/_static/copybutton_funcs.js
pitchmeld/doc/_static/minus.png
pitchmeld/doc/_static/skeleton.css
pitchmeld/doc/_static/basic.css
pitchmeld/doc/_static/pygments.css
pitchmeld/doc/_static/copybutton.css
pitchmeld/doc/_static/doctools.js
pitchmeld/doc/_static/styles/furo.css.map
pitchmeld/doc/_static/styles/furo-extensions.css
pitchmeld/doc/_static/styles/furo.css
pitchmeld/doc/_static/styles/furo-extensions.css.map
pitchmeld/doc/_static/scripts/furo.js.LICENSE.txt
pitchmeld-0.21.3.dist-info/RECORD
pitchmeld-0.21.3.dist-info/WHEEL
pitchmeld-0.21.3.dist-info/top_level.txt
pitchmeld-0.21.3.dist-info/METADATA
pitchmeld-0.21.3.dist-info/licenses/LICENSE.md
