Metadata-Version: 2.4
Name: pitchmeld
Version: 0.21.3
Summary: Please see https://pitchmeld.ing
Home-page: https://doc.pitchmeld.ing
Author: Gilles Degottex
Author-email: dev@pitchmeld.ing
License: LicenseRef-Proprietary
Classifier: Programming Language :: Python :: 3
Classifier: Operating System :: OS Independent
Classifier: Development Status :: 1 - Planning
Classifier: Environment :: Console
Requires-Python: >=3.9
License-File: LICENSE.md
Requires-Dist: numpy>=1.0
Dynamic: author
Dynamic: author-email
Dynamic: classifier
Dynamic: description
Dynamic: description-content-type
Dynamic: home-page
Dynamic: license
Dynamic: license-file
Dynamic: requires-dist
Dynamic: requires-python
Dynamic: summary
